pytorch_brain-0.1.0.dist-info/licenses/LICENSE.txt
torch_brain/__init__.py
torch_brain/optim.py
torch_brain/registry.py
torch_brain/data/__init__.py
torch_brain/data/collate.py
torch_brain/data/dataset.py
torch_brain/data/sampler.py
torch_brain/models/__init__.py
torch_brain/models/poyo.py
torch_brain/models/poyo_plus.py
torch_brain/nn/__init__.py
torch_brain/nn/embedding.py
torch_brain/nn/feedforward.py
torch_brain/nn/infinite_vocab_embedding.py
torch_brain/nn/loss.py
torch_brain/nn/multitask_readout.py
torch_brain/nn/rotary_attention.py
torch_brain/nn/rotary_embedding.py
torch_brain/transforms/__init__.py
torch_brain/transforms/container.py
torch_brain/transforms/output_sampler.py
torch_brain/transforms/random_crop.py
torch_brain/transforms/random_time_scaling.py
torch_brain/transforms/unit_dropout.py
torch_brain/transforms/unit_filter.py
torch_brain/utils/__init__.py
torch_brain/utils/binning.py
torch_brain/utils/callbacks.py
torch_brain/utils/gradient_rescale.py
torch_brain/utils/readout.py
torch_brain/utils/seed_everything.py
torch_brain/utils/sinusoidal_encoding.py
torch_brain/utils/stitcher.py
torch_brain/utils/tokenizers.py
torch_brain/utils/weights.py
pytorch_brain-0.1.0.dist-info/METADATA
pytorch_brain-0.1.0.dist-info/WHEEL
pytorch_brain-0.1.0.dist-info/top_level.txt
pytorch_brain-0.1.0.dist-info/RECORD
